modmlpy/__init__.py
modmlpy/skeleton.py
ModMLPy-0.1.0.dist-info/LICENSE.txt
ModMLPy-0.1.0.dist-info/METADATA
ModMLPy-0.1.0.dist-info/WHEEL
ModMLPy-0.1.0.dist-info/top_level.txt
ModMLPy-0.1.0.dist-info/RECORD
