Metadata-Version: 2.1
Name: ModMLPy
Version: 0.1.0
Summary: ModML Python
Home-page: https://github.com/ModML/ModMLPy/
Author: Alter Ego
Author-email: 0x7c48@gmail.com
License: MIT
Project-URL: Documentation, https://pyscaffold.org/
Platform: any
Classifier: Development Status :: 4 - Beta
Classifier: Programming Language :: Python
License-File: LICENSE.txt
Requires-Dist: importlib-metadata ; python_version < "3.8"
Provides-Extra: testing
Requires-Dist: setuptools ; extra == 'testing'
Requires-Dist: pytest ; extra == 'testing'
Requires-Dist: pytest-cov ; extra == 'testing'
